[{"id":11,"name":"Intel","pending_review":1,"processor_models":["Bronze","Gold","Platinum","Silver"]},{"id":12,"name":"Oracle","pending_review":1,"processor_models":null},{"id":13,"name":"Fujitsu","pending_review":1,"processor_models":null},{"id":14,"name":"IBM","pending_review":1,"processor_models":["E1080","E950","E980","S914","S922","S924"]},{"id":15,"name":"Opteron","pending_review":1,"processor_models":null},{"id":16,"name":"Sun","pending_review":1,"processor_models":null},{"id":17,"name":"HPE","pending_review":1,"processor_models":null},{"id":18,"name":"Oracle","pending_review":1,"processor_models":null},{"id":19,"name":"Fujitsu","pending_review":1,"processor_models":null},{"id":20,"name":"Test_Manufacturer","pending_review":1,"processor_models":null},{"id":21,"name":"Oracle","pending_review":1,"processor_models":null},{"id":22,"name":"Oracle","pending_review":1,"processor_models":null},{"id":25,"name":"Reed_Test","pending_review":1,"processor_models":null},{"id":26,"name":"HP","pending_review":1,"processor_models":null},{"id":27,"name":"HP","pending_review":1,"processor_models":null},{"id":28,"name":"HP","pending_review":1,"processor_models":null},{"id":29,"name":"HP","pending_review":1,"processor_models":null},{"id":30,"name":"Klingon","pending_review":1,"processor_models":null},{"id":31,"name":"New Test1","pending_review":1,"processor_models":null},{"id":32,"name":"New Test2","pending_review":1,"processor_models":null},{"id":33,"name":"asdf","pending_review":1,"processor_models":null},{"id":34,"name":"Cisco","pending_review":1,"processor_models":null},{"id":35,"name":"new mangager","pending_review":1,"processor_models":null},{"id":36,"name":"Reed_Electronics","pending_review":1,"processor_models":null},{"id":37,"name":"IBM Corporation IBM P770","pending_review":1,"processor_models":null},{"id":38,"name":"IBM Corporation P6-570","pending_review":1,"processor_models":null},{"id":39,"name":"IBM Corporation P670","pending_review":1,"processor_models":null},{"id":40,"name":"IBM Corporation P615","pending_review":1,"processor_models":null},{"id":41,"name":"IBM Corporation P730","pending_review":1,"processor_models":null},{"id":42,"name":"IBM Corporation Power 740","pending_review":1,"processor_models":null},{"id":43,"name":"IBM Corporation P520","pending_review":1,"processor_models":null},{"id":44,"name":"IBM Corporation P5-550","pending_review":1,"processor_models":null},{"id":45,"name":"IBM Corporation P710","pending_review":1,"processor_models":null},{"id":46,"name":"IBM Corporation 8247-22L","pending_review":1,"processor_models":null},{"id":47,"name":"IBM Corporation P5-590","pending_review":1,"processor_models":null},{"id":48,"name":"Nutanix","pending_review":1,"processor_models":null},{"id":49,"name":"Dell","pending_review":1,"processor_models":null},{"id":50,"name":"EMC\/DELL","pending_review":1,"processor_models":null},{"id":51,"name":"Dell EMC","pending_review":1,"processor_models":null},{"id":52,"name":"Lenovo","pending_review":1,"processor_models":null},{"id":53,"name":"Datrium","pending_review":1,"processor_models":null},{"id":54,"name":"Datrium License Only","pending_review":1,"processor_models":null},{"id":55,"name":"","pending_review":1,"processor_models":null},{"id":56,"name":"Cloudistics","pending_review":1,"processor_models":null},{"id":57,"name":"750","pending_review":1,"processor_models":null},{"id":58,"name":"570","pending_review":1,"processor_models":null},{"id":59,"name":"770","pending_review":1,"processor_models":null},{"id":60,"name":"AMD","pending_review":1,"processor_models":[]},{"id":61,"name":"LENOVO","pending_review":1,"processor_models":null},{"id":62,"name":"E880C","pending_review":1,"processor_models":null},{"id":63,"name":"8234","pending_review":1,"processor_models":null},{"id":64,"name":"9133","pending_review":1,"processor_models":null},{"id":65,"name":"9113","pending_review":1,"processor_models":null},{"id":66,"name":"8233","pending_review":1,"processor_models":null},{"id":67,"name":"Dell Inc.","pending_review":1,"processor_models":null},{"id":68,"name":"Cisco Systems Inc","pending_review":1,"processor_models":null},{"id":69,"name":"ddcamresx02.emsc.root01.org","pending_review":1,"processor_models":null},{"id":70,"name":"ddcdmzesx06.emsc.root01.org","pending_review":1,"processor_models":null},{"id":71,"name":"ddcdmzesx01.emsc.root01.org","pending_review":1,"processor_models":null},{"id":72,"name":"ddcamresx13.emsc.root01.org","pending_review":1,"processor_models":null},{"id":73,"name":"ddcemcesx04.emsc.root01.org","pending_review":1,"processor_models":null},{"id":74,"name":"ddcamresx01.emsc.root01.org","pending_review":1,"processor_models":null},{"id":75,"name":"ddcdmzesx02.emsc.root01.org","pending_review":1,"processor_models":null},{"id":76,"name":"ddcemcesx06.emsc.root01.org","pending_review":1,"processor_models":null},{"id":77,"name":"ddcamresx03.emsc.root01.org","pending_review":1,"processor_models":null},{"id":78,"name":"ddcemcesx05.emsc.root01.org","pending_review":1,"processor_models":null},{"id":79,"name":"ddcamresx15.emsc.root01.org","pending_review":1,"processor_models":null},{"id":80,"name":"ddcevhesx04.emsc.root01.org","pending_review":1,"processor_models":null},{"id":81,"name":"ddcesxucs07.emsc.root01.org","pending_review":1,"processor_models":null},{"id":82,"name":"ddcamresx14.emsc.root01.org","pending_review":1,"processor_models":null},{"id":83,"name":"ddcdmzesx05.emsc.root01.org","pending_review":1,"processor_models":null},{"id":84,"name":"ddcemcesx02.emsc.root01.org","pending_review":1,"processor_models":null},{"id":85,"name":"ddcamresx05.emsc.root01.org","pending_review":1,"processor_models":null},{"id":86,"name":"ddcamresx04.emsc.root01.org","pending_review":1,"processor_models":null},{"id":87,"name":"ddcdmzesx04.emsc.root01.org","pending_review":1,"processor_models":null},{"id":88,"name":"ddcdmzesx03.emsc.root01.org","pending_review":1,"processor_models":null},{"id":89,"name":"ddcemcesx03.emsc.root01.org","pending_review":1,"processor_models":null},{"id":90,"name":"ddcevhesx06.emsc.root01.org","pending_review":1,"processor_models":null},{"id":91,"name":"ddcvsphereucs11.emsc.root01.org","pending_review":1,"processor_models":null},{"id":92,"name":"ddcevhesx02.emsc.root01.org","pending_review":1,"processor_models":null},{"id":93,"name":"ddcevhesx05.emsc.root01.org","pending_review":1,"processor_models":null},{"id":94,"name":"ddcvsphereucs1.emsc.root01.org","pending_review":1,"processor_models":null},{"id":95,"name":"ddcvsphere02.emsc.root01.org","pending_review":1,"processor_models":null},{"id":96,"name":"ddcvsphereucs26.emsc.root01.org","pending_review":1,"processor_models":null},{"id":97,"name":"ddcvsphereucs20.emsc.root01.org","pending_review":1,"processor_models":null},{"id":98,"name":"ddcvsphereucs28.emsc.root01.org","pending_review":1,"processor_models":null},{"id":99,"name":"ddcvsphereucs15.emsc.root01.org","pending_review":1,"processor_models":null},{"id":100,"name":"ddcvsphereucs10.emsc.root01.org","pending_review":1,"processor_models":null},{"id":101,"name":"ddcvsphere01.emsc.root01.org","pending_review":1,"processor_models":null},{"id":102,"name":"ddcvsphereucs6.emsc.root01.org","pending_review":1,"processor_models":null},{"id":103,"name":"ddcvsphereucs37.emsc.root01.org","pending_review":1,"processor_models":null},{"id":104,"name":"ddcvsphereucs8.emsc.root01.org","pending_review":1,"processor_models":null},{"id":105,"name":"flwldesx02.emsc.root01.org","pending_review":1,"processor_models":null},{"id":106,"name":"ddcvsphereucs34.emsc.root01.org","pending_review":1,"processor_models":null},{"id":107,"name":"ddcvsphereucs23.emsc.root01.org","pending_review":1,"processor_models":null},{"id":108,"name":"ddcvsphereucs17.emsc.root01.org","pending_review":1,"processor_models":null},{"id":109,"name":"ddcvsphereucs19.emsc.root01.org","pending_review":1,"processor_models":null},{"id":110,"name":"ddcvsphereucs13.emsc.root01.org","pending_review":1,"processor_models":null},{"id":111,"name":"ddcvsphereucs12.emsc.root01.org","pending_review":1,"processor_models":null},{"id":112,"name":"ddcvsphereucs32.emsc.root01.org","pending_review":1,"processor_models":null},{"id":113,"name":"ddcvsphereucs47.emsc.root01.org","pending_review":1,"processor_models":null},{"id":114,"name":"ddcvsphereucs49.emsc.root01.org","pending_review":1,"processor_models":null},{"id":115,"name":"ddcvsphereucs43.emsc.root01.org","pending_review":1,"processor_models":null},{"id":116,"name":"ddcvsphere03.emsc.root01.org","pending_review":1,"processor_models":null},{"id":117,"name":"ddcvsphereucs40.emsc.root01.org","pending_review":1,"processor_models":null},{"id":118,"name":"ddcvsphereucs39.emsc.root01.org","pending_review":1,"processor_models":null},{"id":119,"name":"ddcvsphereucs3.emsc.root01.org","pending_review":1,"processor_models":null},{"id":120,"name":"ddcvsphereucs27.emsc.root01.org","pending_review":1,"processor_models":null},{"id":121,"name":"ddcvsphereucs21.emsc.root01.org","pending_review":1,"processor_models":null},{"id":122,"name":"ddcvsphereucs24.emsc.root01.org","pending_review":1,"processor_models":null},{"id":123,"name":"ddcvsphereucs5.emsc.root01.org","pending_review":1,"processor_models":null},{"id":124,"name":"ddcvsphereucs36.emsc.root01.org","pending_review":1,"processor_models":null},{"id":125,"name":"ddcvsphereucs33.emsc.root01.org","pending_review":1,"processor_models":null},{"id":126,"name":"ddcvsphereucs42.emsc.root01.org","pending_review":1,"processor_models":null},{"id":127,"name":"flwldesx03.emsc.root01.org","pending_review":1,"processor_models":null},{"id":128,"name":"ddcvsphereucs18.emsc.root01.org","pending_review":1,"processor_models":null},{"id":129,"name":"ddcvsphereucs2.emsc.root01.org","pending_review":1,"processor_models":null},{"id":130,"name":"ddcvsphereucs16.emsc.root01.org","pending_review":1,"processor_models":null},{"id":131,"name":"ddcvsphereucs14.emsc.root01.org","pending_review":1,"processor_models":null},{"id":132,"name":"ddcvsphereucs9.emsc.root01.org","pending_review":1,"processor_models":null},{"id":133,"name":"ddcvsphereucs48.emsc.root01.org","pending_review":1,"processor_models":null},{"id":134,"name":"ddcvsphereucs4.emsc.root01.org","pending_review":1,"processor_models":null},{"id":135,"name":"ddcvsphereucs7.emsc.root01.org","pending_review":1,"processor_models":null},{"id":136,"name":"ddcvsphereucs38.emsc.root01.org","pending_review":1,"processor_models":null},{"id":137,"name":"ddcvsphereucs46.emsc.root01.org","pending_review":1,"processor_models":null},{"id":138,"name":"IBM","pending_review":1,"processor_models":null},{"id":139,"name":"x86","pending_review":1,"processor_models":null},{"id":140,"name":"HC Mfg.","pending_review":1,"processor_models":null},{"id":141,"name":"IBM","pending_review":1,"processor_models":null},{"id":142,"name":"IBM","pending_review":1,"processor_models":null},{"id":143,"name":"IBM","pending_review":1,"processor_models":null},{"id":144,"name":"IBM","pending_review":1,"processor_models":null},{"id":145,"name":"IBM","pending_review":1,"processor_models":null},{"id":146,"name":"IBM","pending_review":1,"processor_models":null},{"id":147,"name":"IBM","pending_review":1,"processor_models":null},{"id":148,"name":"IBM","pending_review":1,"processor_models":null},{"id":149,"name":"IBM","pending_review":1,"processor_models":null},{"id":150,"name":"IBM","pending_review":1,"processor_models":null},{"id":151,"name":"sample","pending_review":1,"processor_models":null},{"id":152,"name":"DB","pending_review":1,"processor_models":null},{"id":153,"name":"HCI","pending_review":1,"processor_models":null},{"id":154,"name":"OVH","pending_review":1,"processor_models":null},{"id":155,"name":"Hyperconverged","pending_review":1,"processor_models":null},{"id":156,"name":"Oracle-SUN","pending_review":1,"processor_models":null},{"id":157,"name":"Prod","pending_review":1,"processor_models":null},{"id":158,"name":"Mellanox","pending_review":1,"processor_models":null},{"id":159,"name":"Cisco HyperFlex","pending_review":1,"processor_models":null},{"id":160,"name":"DELL","pending_review":1,"processor_models":null},{"id":161,"name":"CISCO","pending_review":1,"processor_models":null},{"id":162,"name":"Super Micro","pending_review":1,"processor_models":null},{"id":163,"name":"Xeon E5430","pending_review":1,"processor_models":null},{"id":164,"name":"CPS Hosting","pending_review":1,"processor_models":null},{"id":165,"name":"IBM","pending_review":1,"processor_models":null},{"id":166,"name":"MSI","pending_review":1,"processor_models":null},{"id":167,"name":"Intel Corporation","pending_review":1,"processor_models":null},{"id":168,"name":"Supermicro","pending_review":1,"processor_models":null},{"id":169,"name":"NetApp","pending_review":1,"processor_models":null},{"id":170,"name":"Generic","pending_review":1,"processor_models":null},{"id":171,"name":"s","pending_review":1,"processor_models":null},{"id":172,"name":"Oracle DB","pending_review":1,"processor_models":null},{"id":173,"name":"Cisco Systems, Inc.","pending_review":1,"processor_models":null},{"id":174,"name":"Cisco Systems, Inc.","pending_review":1,"processor_models":null},{"id":175,"name":"IBM","pending_review":1,"processor_models":null},{"id":176,"name":"IBM","pending_review":1,"processor_models":null},{"id":177,"name":"IBM","pending_review":1,"processor_models":null},{"id":178,"name":"IBM","pending_review":1,"processor_models":null},{"id":179,"name":"IBM","pending_review":1,"processor_models":null},{"id":180,"name":"IBM","pending_review":1,"processor_models":null},{"id":181,"name":"IBM","pending_review":1,"processor_models":null},{"id":182,"name":"IBM","pending_review":1,"processor_models":null},{"id":183,"name":"IBM","pending_review":1,"processor_models":null},{"id":184,"name":"IBM","pending_review":1,"processor_models":null},{"id":185,"name":"IBM","pending_review":1,"processor_models":null},{"id":186,"name":"IBM","pending_review":1,"processor_models":null},{"id":187,"name":"IBM","pending_review":1,"processor_models":null},{"id":188,"name":"IBM","pending_review":1,"processor_models":null},{"id":189,"name":"IBM","pending_review":1,"processor_models":null},{"id":190,"name":"n","pending_review":1,"processor_models":null},{"id":191,"name":"IBM2","pending_review":1,"processor_models":null},{"id":192,"name":"Cores\/processor or Total Cores","pending_review":1,"processor_models":null},{"id":193,"name":"Cores\/processor or Total Cores","pending_review":1,"processor_models":null},{"id":194,"name":"Cores\/processor or Total Cores","pending_review":1,"processor_models":null},{"id":195,"name":"Quanta","pending_review":1,"processor_models":null},{"id":196,"name":"www","pending_review":1,"processor_models":null},{"id":197,"name":"Test_Jenny","pending_review":1,"processor_models":null},{"id":198,"name":"sample converged","pending_review":1,"processor_models":null},{"id":199,"name":"VMware","pending_review":1,"processor_models":null},{"id":200,"name":"Dell\/EMC","pending_review":1,"processor_models":null},{"id":201,"name":"IBM","pending_review":1,"processor_models":null},{"id":202,"name":"IBM","pending_review":1,"processor_models":null},{"id":203,"name":"IBM","pending_review":1,"processor_models":null},{"id":204,"name":"IBM","pending_review":1,"processor_models":null},{"id":205,"name":"HP Itanium","pending_review":1,"processor_models":null},{"id":206,"name":"HP 9000","pending_review":1,"processor_models":null},{"id":207,"name":"Sun Microsystem T5440","pending_review":1,"processor_models":null},{"id":208,"name":"HP 9000\/800","pending_review":1,"processor_models":null},{"id":209,"name":"Sun Microsystems","pending_review":1,"processor_models":null},{"id":210,"name":"PC","pending_review":1,"processor_models":null},{"id":211,"name":"Sun Oracle","pending_review":1,"processor_models":null},{"id":212,"name":"Sun Microsystem T5120","pending_review":1,"processor_models":null},{"id":213,"name":"PC","pending_review":1,"processor_models":null},{"id":214,"name":"Sun Microsystems","pending_review":1,"processor_models":null},{"id":215,"name":"HP Itanium","pending_review":1,"processor_models":null},{"id":216,"name":"Sun Oracle","pending_review":1,"processor_models":null},{"id":217,"name":"HP 9000","pending_review":1,"processor_models":null},{"id":218,"name":"Sun Microsystem T5120","pending_review":1,"processor_models":null},{"id":219,"name":"HP 9000\/800","pending_review":1,"processor_models":null},{"id":220,"name":"Sun Microsystem T5440","pending_review":1,"processor_models":null},{"id":221,"name":"IBM","pending_review":1,"processor_models":null},{"id":222,"name":"IBM","pending_review":1,"processor_models":null},{"id":223,"name":"IBM","pending_review":1,"processor_models":null},{"id":224,"name":"IBM","pending_review":1,"processor_models":null},{"id":225,"name":"IBM","pending_review":1,"processor_models":null},{"id":226,"name":"IBM","pending_review":1,"processor_models":null},{"id":227,"name":"IBM","pending_review":1,"processor_models":null},{"id":228,"name":"IBM","pending_review":1,"processor_models":null},{"id":229,"name":"IBM","pending_review":1,"processor_models":null},{"id":230,"name":"IBM","pending_review":1,"processor_models":null},{"id":231,"name":"IBM","pending_review":1,"processor_models":null},{"id":232,"name":"IBM","pending_review":1,"processor_models":null},{"id":233,"name":"IBM","pending_review":1,"processor_models":null},{"id":234,"name":"IBM","pending_review":1,"processor_models":null},{"id":235,"name":"IBM","pending_review":1,"processor_models":null},{"id":236,"name":"IBM","pending_review":1,"processor_models":null},{"id":237,"name":"IBM","pending_review":1,"processor_models":null},{"id":238,"name":"IBM","pending_review":1,"processor_models":null},{"id":239,"name":"IBM","pending_review":1,"processor_models":null},{"id":240,"name":"IBM","pending_review":1,"processor_models":null},{"id":241,"name":"IBM","pending_review":1,"processor_models":null},{"id":242,"name":"IBM","pending_review":1,"processor_models":null},{"id":243,"name":"IBM","pending_review":1,"processor_models":null},{"id":244,"name":"IBM","pending_review":1,"processor_models":null},{"id":245,"name":"IBM","pending_review":1,"processor_models":null},{"id":246,"name":"IBM","pending_review":1,"processor_models":null},{"id":247,"name":"IBM","pending_review":1,"processor_models":null},{"id":248,"name":"IBM","pending_review":1,"processor_models":null},{"id":249,"name":"IBM","pending_review":1,"processor_models":null},{"id":250,"name":"Apple Inc.","pending_review":1,"processor_models":null},{"id":251,"name":"IBM","pending_review":1,"processor_models":null},{"id":252,"name":"IBM","pending_review":1,"processor_models":null},{"id":253,"name":"IBM","pending_review":1,"processor_models":null},{"id":254,"name":"IBM","pending_review":1,"processor_models":null},{"id":255,"name":"IBM","pending_review":1,"processor_models":null},{"id":256,"name":"IBM","pending_review":1,"processor_models":null},{"id":257,"name":"IBM","pending_review":1,"processor_models":null},{"id":258,"name":"IBM","pending_review":1,"processor_models":null},{"id":259,"name":"IBM","pending_review":1,"processor_models":null},{"id":260,"name":"VMware, Inc.","pending_review":1,"processor_models":null},{"id":261,"name":"VMware Cloud on AWS","pending_review":1,"processor_models":null},{"id":262,"name":"usage test","pending_review":1,"processor_models":null},{"id":263,"name":"usage test 2","pending_review":1,"processor_models":null},{"id":264,"name":"Meridian","pending_review":1,"processor_models":null},{"id":265,"name":"Meridian Cloud","pending_review":1,"processor_models":null},{"id":266,"name":"meridian cloud server","pending_review":1,"processor_models":null},{"id":267,"name":"haydn sample server","pending_review":1,"processor_models":null},{"id":268,"name":"haydn sample 2","pending_review":1,"processor_models":null},{"id":269,"name":"haydn conv 1","pending_review":1,"processor_models":null},{"id":270,"name":"IBM Cloud Sample","pending_review":1,"processor_models":null},{"id":271,"name":"Customer Internal Cloud","pending_review":1,"processor_models":null},{"id":272,"name":"IBM","pending_review":1,"processor_models":null},{"id":273,"name":"IBM","pending_review":1,"processor_models":null},{"id":274,"name":"AWS Outpost","pending_review":1,"processor_models":null},{"id":275,"name":"Inrel","pending_review":1,"processor_models":null},{"id":276,"name":"Product Company","pending_review":1,"processor_models":null},{"id":277,"name":"IBM test","pending_review":1,"processor_models":null},{"id":278,"name":"test","pending_review":1,"processor_models":null},{"id":279,"name":"TidalScale","pending_review":1,"processor_models":null},{"id":280,"name":"Riverbed","pending_review":1,"processor_models":null},{"id":281,"name":"IBM","pending_review":1,"processor_models":null},{"id":282,"name":"IBM Cloud","pending_review":1,"processor_models":null},{"id":283,"name":"IBM","pending_review":1,"processor_models":null},{"id":284,"name":"IBM","pending_review":1,"processor_models":null},{"id":285,"name":"IBM","pending_review":1,"processor_models":null},{"id":286,"name":"IBM","pending_review":1,"processor_models":null},{"id":287,"name":"AIX","pending_review":1,"processor_models":null},{"id":288,"name":"IBM E950 3.15 test","pending_review":1,"processor_models":null},{"id":289,"name":"IBM","pending_review":1,"processor_models":null},{"id":290,"name":"IBM","pending_review":1,"processor_models":null},{"id":291,"name":"IBM","pending_review":1,"processor_models":null},{"id":292,"name":"IBM","pending_review":1,"processor_models":null},{"id":293,"name":"IBM","pending_review":1,"processor_models":null},{"id":294,"name":"IBM","pending_review":1,"processor_models":null},{"id":295,"name":"IBM","pending_review":1,"processor_models":null},{"id":296,"name":"IBM","pending_review":1,"processor_models":null},{"id":297,"name":"IBM","pending_review":1,"processor_models":null},{"id":298,"name":"IBM","pending_review":1,"processor_models":null},{"id":299,"name":"IBM","pending_review":1,"processor_models":null},{"id":300,"name":"IBM","pending_review":1,"processor_models":null},{"id":301,"name":"IBM","pending_review":1,"processor_models":null},{"id":302,"name":"IBM","pending_review":1,"processor_models":null},{"id":303,"name":"IBM","pending_review":1,"processor_models":null},{"id":304,"name":"IBM","pending_review":1,"processor_models":null},{"id":305,"name":"DL380","pending_review":1,"processor_models":null},{"id":306,"name":"Other","pending_review":1,"processor_models":null},{"id":307,"name":"Other","pending_review":1,"processor_models":null},{"id":308,"name":"AMD *","pending_review":1,"processor_models":[]},{"id":309,"name":"Vendor","pending_review":1,"processor_models":null},{"id":310,"name":"N\/A","pending_review":1,"processor_models":null},{"id":311,"name":"I","pending_review":1,"processor_models":null}]